reports_utfunc/__init__.py
riskpackage/__init__.py
riskpackage-0.0.1.dist-info/METADATA
riskpackage-0.0.1.dist-info/WHEEL
riskpackage-0.0.1.dist-info/top_level.txt
riskpackage-0.0.1.dist-info/RECORD
