Metadata-Version: 2.1
Name: riskpackage
Version: 0.0.1
Summary: this is a risk package
Home-page: UNKNOWN
Author: Abhay
Author-email: abhayiitk7@gmail.com
License: UNKNOWN
Platform: UNKNOWN
Classifier: Programming Language :: Python :: 3
Classifier: License :: OSI Approved :: MIT License
Classifier: Operating System :: OS Independent
Requires-Python: >=3.6
